{
"17000": {"fire_mode_id":17000,"item_id":"17012","type":"primary","description":{"de":"Automatik","en":"Auto","es":"Automático","fr":"Automatique","it":"Automatico","tr":"Otomatik"},"player_state_group_id":"2032","cof_recoil":"0.06","reload_time_ms":"2000","reload_chamber_time_ms":"700","pellets_per_shot":"1","pellet_spread":"0","default_zoom":"1","muzzle_velocity":"450","speed":"400","damage_radius":"0","projectile_description":"VS MAX - Light Bullet VS (0-30mm)","damage_type":"DamageFalloff","damage_min":"143","damage_max":"167","damage_min_range":"75","damage_max_range":"10","damage_target_type":"2","damage_resist_type":"2"}
,"17000": {"fire_mode_id":17000,"item_id":"17000","type":"primary","description":{"de":"Automatik","en":"Auto","es":"Automático","fr":"Automatique","it":"Automatico","tr":"Otomatik"},"player_state_group_id":"2032","cof_recoil":"0.06","reload_time_ms":"2000","reload_chamber_time_ms":"700","pellets_per_shot":"1","pellet_spread":"0","default_zoom":"1","muzzle_velocity":"450","speed":"400","damage_radius":"0","projectile_description":"VS MAX - Light Bullet VS (0-30mm)","damage_type":"DamageFalloff","damage_min":"143","damage_max":"167","damage_min_range":"75","damage_max_range":"10","damage_target_type":"2","damage_resist_type":"2"}
,"17001": {"fire_mode_id":17001,"item_id":"17013","type":"primary","description":{"de":"Automatik","en":"Auto","es":"Automático","fr":"Automatique","it":"Automatico","tr":"Otomatik"},"player_state_group_id":"2037","cof_recoil":"0","reload_time_ms":"1350","reload_chamber_time_ms":"150","pellets_per_shot":"1","pellet_spread":"0","default_zoom":"1","speed":"75","max_speed":"0","damage_radius":"1","projectile_description":"VS: MAX: Anti Vehicle 01: Comet","damage_type":"Damage","damage":"175","damage_resist_type":"5","indirect_damage_max":"100","indirect_damage_max_range":"0.5","indirect_damage_min":"25","indirect_damage_min_range":"3","indirect_damage_target_type":"2","indirect_damage_resist_type":"6"}
,"17001": {"fire_mode_id":17001,"item_id":"17001","type":"primary","description":{"de":"Automatik","en":"Auto","es":"Automático","fr":"Automatique","it":"Automatico","tr":"Otomatik"},"player_state_group_id":"2037","cof_recoil":"0","reload_time_ms":"1350","reload_chamber_time_ms":"150","pellets_per_shot":"1","pellet_spread":"0","default_zoom":"1","speed":"75","max_speed":"0","damage_radius":"1","projectile_description":"VS: MAX: Anti Vehicle 01: Comet","damage_type":"Damage","damage":"175","damage_resist_type":"5","indirect_damage_max":"100","indirect_damage_max_range":"0.5","indirect_damage_min":"25","indirect_damage_min_range":"3","indirect_damage_target_type":"2","indirect_damage_resist_type":"6"}
,"17004": {"fire_mode_id":17004,"item_id":"804745","type":"primary","description":{"de":"Automatik","en":"Auto","es":"Automático","fr":"Automatique","it":"Automatico","tr":"Otomatik"},"player_state_group_id":"2039","cof_recoil":"0","reload_time_ms":"3000","reload_chamber_time_ms":"500","pellets_per_shot":"1","pellet_spread":"0","default_zoom":"1","speed":"325","max_speed":"0","damage_radius":"1","projectile_description":"VS MAX - Burster Flak Bullet (0-30mm)","damage_type":"DamageFalloff","damage_min":"20","damage_max":"100","damage_min_range":"200","damage_max_range":"50","damage_target_type":"2","damage_resist_type":"4","indirect_damage_max":"28","indirect_damage_max_range":"5","indirect_damage_min":"1","indirect_damage_min_range":"8","indirect_damage_target_type":"2","indirect_damage_resist_type":"12"}
,"17004": {"fire_mode_id":17004,"item_id":"800810","type":"primary","description":{"de":"Automatik","en":"Auto","es":"Automático","fr":"Automatique","it":"Automatico","tr":"Otomatik"},"player_state_group_id":"2039","cof_recoil":"0","reload_time_ms":"3000","reload_chamber_time_ms":"500","pellets_per_shot":"1","pellet_spread":"0","default_zoom":"1","speed":"325","max_speed":"0","damage_radius":"1","projectile_description":"VS MAX - Burster Flak Bullet (0-30mm)","damage_type":"DamageFalloff","damage_min":"20","damage_max":"100","damage_min_range":"200","damage_max_range":"50","damage_target_type":"2","damage_resist_type":"4","indirect_damage_max":"28","indirect_damage_max_range":"5","indirect_damage_min":"1","indirect_damage_min_range":"8","indirect_damage_target_type":"2","indirect_damage_resist_type":"12"}
,"17004": {"fire_mode_id":17004,"item_id":"17016","type":"primary","description":{"de":"Automatik","en":"Auto","es":"Automático","fr":"Automatique","it":"Automatico","tr":"Otomatik"},"player_state_group_id":"2039","cof_recoil":"0","reload_time_ms":"3000","reload_chamber_time_ms":"500","pellets_per_shot":"1","pellet_spread":"0","default_zoom":"1","speed":"325","max_speed":"0","damage_radius":"1","projectile_description":"VS MAX - Burster Flak Bullet (0-30mm)","damage_type":"DamageFalloff","damage_min":"20","damage_max":"100","damage_min_range":"200","damage_max_range":"50","damage_target_type":"2","damage_resist_type":"4","indirect_damage_max":"28","indirect_damage_max_range":"5","indirect_damage_min":"1","indirect_damage_min_range":"8","indirect_damage_target_type":"2","indirect_damage_resist_type":"12"}
,"17004": {"fire_mode_id":17004,"item_id":"804752","type":"primary","description":{"de":"Automatik","en":"Auto","es":"Automático","fr":"Automatique","it":"Automatico","tr":"Otomatik"},"player_state_group_id":"2039","cof_recoil":"0","reload_time_ms":"3000","reload_chamber_time_ms":"500","pellets_per_shot":"1","pellet_spread":"0","default_zoom":"1","speed":"325","max_speed":"0","damage_radius":"1","projectile_description":"VS MAX - Burster Flak Bullet (0-30mm)","damage_type":"DamageFalloff","damage_min":"20","damage_max":"100","damage_min_range":"200","damage_max_range":"50","damage_target_type":"2","damage_resist_type":"4","indirect_damage_max":"28","indirect_damage_max_range":"5","indirect_damage_min":"1","indirect_damage_min_range":"8","indirect_damage_target_type":"2","indirect_damage_resist_type":"12"}
,"17004": {"fire_mode_id":17004,"item_id":"804751","type":"primary","description":{"de":"Automatik","en":"Auto","es":"Automático","fr":"Automatique","it":"Automatico","tr":"Otomatik"},"player_state_group_id":"2039","cof_recoil":"0","reload_time_ms":"3000","reload_chamber_time_ms":"500","pellets_per_shot":"1","pellet_spread":"0","default_zoom":"1","speed":"325","max_speed":"0","damage_radius":"1","projectile_description":"VS MAX - Burster Flak Bullet (0-30mm)","damage_type":"DamageFalloff","damage_min":"20","damage_max":"100","damage_min_range":"200","damage_max_range":"50","damage_target_type":"2","damage_resist_type":"4","indirect_damage_max":"28","indirect_damage_max_range":"5","indirect_damage_min":"1","indirect_damage_min_range":"8","indirect_damage_target_type":"2","indirect_damage_resist_type":"12"}
,"17004": {"fire_mode_id":17004,"item_id":"800811","type":"primary","description":{"de":"Automatik","en":"Auto","es":"Automático","fr":"Automatique","it":"Automatico","tr":"Otomatik"},"player_state_group_id":"2039","cof_recoil":"0","reload_time_ms":"3000","reload_chamber_time_ms":"500","pellets_per_shot":"1","pellet_spread":"0","default_zoom":"1","speed":"325","max_speed":"0","damage_radius":"1","projectile_description":"VS MAX - Burster Flak Bullet (0-30mm)","damage_type":"DamageFalloff","damage_min":"20","damage_max":"100","damage_min_range":"200","damage_max_range":"50","damage_target_type":"2","damage_resist_type":"4","indirect_damage_max":"28","indirect_damage_max_range":"5","indirect_damage_min":"1","indirect_damage_min_range":"8","indirect_damage_target_type":"2","indirect_damage_resist_type":"12"}
,"17004": {"fire_mode_id":17004,"item_id":"804746","type":"primary","description":{"de":"Automatik","en":"Auto","es":"Automático","fr":"Automatique","it":"Automatico","tr":"Otomatik"},"player_state_group_id":"2039","cof_recoil":"0","reload_time_ms":"3000","reload_chamber_time_ms":"500","pellets_per_shot":"1","pellet_spread":"0","default_zoom":"1","speed":"325","max_speed":"0","damage_radius":"1","projectile_description":"VS MAX - Burster Flak Bullet (0-30mm)","damage_type":"DamageFalloff","damage_min":"20","damage_max":"100","damage_min_range":"200","damage_max_range":"50","damage_target_type":"2","damage_resist_type":"4","indirect_damage_max":"28","indirect_damage_max_range":"5","indirect_damage_min":"1","indirect_damage_min_range":"8","indirect_damage_target_type":"2","indirect_damage_resist_type":"12"}
,"17004": {"fire_mode_id":17004,"item_id":"800817","type":"primary","description":{"de":"Automatik","en":"Auto","es":"Automático","fr":"Automatique","it":"Automatico","tr":"Otomatik"},"player_state_group_id":"2039","cof_recoil":"0","reload_time_ms":"3000","reload_chamber_time_ms":"500","pellets_per_shot":"1","pellet_spread":"0","default_zoom":"1","speed":"325","max_speed":"0","damage_radius":"1","projectile_description":"VS MAX - Burster Flak Bullet (0-30mm)","damage_type":"DamageFalloff","damage_min":"20","damage_max":"100","damage_min_range":"200","damage_max_range":"50","damage_target_type":"2","damage_resist_type":"4","indirect_damage_max":"28","indirect_damage_max_range":"5","indirect_damage_min":"1","indirect_damage_min_range":"8","indirect_damage_target_type":"2","indirect_damage_resist_type":"12"}
,"17004": {"fire_mode_id":17004,"item_id":"17004","type":"primary","description":{"de":"Automatik","en":"Auto","es":"Automático","fr":"Automatique","it":"Automatico","tr":"Otomatik"},"player_state_group_id":"2039","cof_recoil":"0","reload_time_ms":"3000","reload_chamber_time_ms":"500","pellets_per_shot":"1","pellet_spread":"0","default_zoom":"1","speed":"325","max_speed":"0","damage_radius":"1","projectile_description":"VS MAX - Burster Flak Bullet (0-30mm)","damage_type":"DamageFalloff","damage_min":"20","damage_max":"100","damage_min_range":"200","damage_max_range":"50","damage_target_type":"2","damage_resist_type":"4","indirect_damage_max":"28","indirect_damage_max_range":"5","indirect_damage_min":"1","indirect_damage_min_range":"8","indirect_damage_target_type":"2","indirect_damage_resist_type":"12"}
,"17004": {"fire_mode_id":17004,"item_id":"800816","type":"primary","description":{"de":"Automatik","en":"Auto","es":"Automático","fr":"Automatique","it":"Automatico","tr":"Otomatik"},"player_state_group_id":"2039","cof_recoil":"0","reload_time_ms":"3000","reload_chamber_time_ms":"500","pellets_per_shot":"1","pellet_spread":"0","default_zoom":"1","speed":"325","max_speed":"0","damage_radius":"1","projectile_description":"VS MAX - Burster Flak Bullet (0-30mm)","damage_type":"DamageFalloff","damage_min":"20","damage_max":"100","damage_min_range":"200","damage_max_range":"50","damage_target_type":"2","damage_resist_type":"4","indirect_damage_max":"28","indirect_damage_max_range":"5","indirect_damage_min":"1","indirect_damage_min_range":"8","indirect_damage_target_type":"2","indirect_damage_resist_type":"12"}
,"17200": {"fire_mode_id":17200,"item_id":"6002896","type":"primary","description":{"de":"Halbautomatik","en":"Semi-Auto","es":"Semiautomático","fr":"Semi-automatique","it":"Semiautomatico","tr":"Yarı Otomatik"},"player_state_group_id":"2045","cof_recoil":"0.1","reload_time_ms":"2455","reload_chamber_time_ms":"845","pellets_per_shot":"1","pellet_spread":"0","default_zoom":"1","muzzle_velocity":"600","speed":"600","max_speed":"0","projectile_description":"NC Assault Rifle: Mid","damage_type":"DamageFalloff","damage_min":"100","damage_max":"143","damage_min_range":"60","damage_max_range":"10","damage_target_type":"2","damage_resist_type":"2"}
,"17200": {"fire_mode_id":17200,"item_id":"920","type":"primary","description":{"de":"Halbautomatik","en":"Semi-Auto","es":"Semiautomático","fr":"Semi-automatique","it":"Semiautomatico","tr":"Yarı Otomatik"},"player_state_group_id":"2045","cof_recoil":"0.1","reload_time_ms":"2455","reload_chamber_time_ms":"845","pellets_per_shot":"1","pellet_spread":"0","default_zoom":"1","muzzle_velocity":"600","speed":"600","max_speed":"0","projectile_description":"NC Assault Rifle: Mid","damage_type":"DamageFalloff","damage_min":"100","damage_max":"143","damage_min_range":"60","damage_max_range":"10","damage_target_type":"2","damage_resist_type":"2"}
,"17200": {"fire_mode_id":17200,"item_id":"50020","type":"primary","description":{"de":"Halbautomatik","en":"Semi-Auto","es":"Semiautomático","fr":"Semi-automatique","it":"Semiautomatico","tr":"Yarı Otomatik"},"player_state_group_id":"2045","cof_recoil":"0.1","reload_time_ms":"2455","reload_chamber_time_ms":"845","pellets_per_shot":"1","pellet_spread":"0","default_zoom":"1","muzzle_velocity":"600","speed":"600","max_speed":"0","projectile_description":"NC Assault Rifle: Mid","damage_type":"DamageFalloff","damage_min":"100","damage_max":"143","damage_min_range":"60","damage_max_range":"10","damage_target_type":"2","damage_resist_type":"2"}
,"17200": {"fire_mode_id":17200,"item_id":"73","type":"primary","description":{"de":"Halbautomatik","en":"Semi-Auto","es":"Semiautomático","fr":"Semi-automatique","it":"Semiautomatico","tr":"Yarı Otomatik"},"player_state_group_id":"2045","cof_recoil":"0.1","reload_time_ms":"2455","reload_chamber_time_ms":"845","pellets_per_shot":"1","pellet_spread":"0","default_zoom":"1","muzzle_velocity":"600","speed":"600","max_speed":"0","projectile_description":"NC Assault Rifle: Mid","damage_type":"DamageFalloff","damage_min":"100","damage_max":"143","damage_min_range":"60","damage_max_range":"10","damage_target_type":"2","damage_resist_type":"2"}
,"17200": {"fire_mode_id":17200,"item_id":"800880","type":"primary","description":{"de":"Halbautomatik","en":"Semi-Auto","es":"Semiautomático","fr":"Semi-automatique","it":"Semiautomatico","tr":"Yarı Otomatik"},"player_state_group_id":"2045","cof_recoil":"0.1","reload_time_ms":"2455","reload_chamber_time_ms":"845","pellets_per_shot":"1","pellet_spread":"0","default_zoom":"1","muzzle_velocity":"600","speed":"600","max_speed":"0","projectile_description":"NC Assault Rifle: Mid","damage_type":"DamageFalloff","damage_min":"100","damage_max":"143","damage_min_range":"60","damage_max_range":"10","damage_target_type":"2","damage_resist_type":"2"}
,"17208": {"fire_mode_id":17208,"item_id":"7108","type":"primary","description":{"de":"Halbautomatik","en":"Semi-Auto","es":"Semiautomático","fr":"Semi-automatique","it":"Semiautomatico","tr":"Yarı Otomatik"},"player_state_group_id":"2099","cof_recoil":"0.14","reload_time_ms":"1925","reload_chamber_time_ms":"640","pellets_per_shot":"1","pellet_spread":"0","default_zoom":"1","muzzle_velocity":"615","speed":"550","max_speed":"0","damage_radius":"0","projectile_description":"NC Assault Rifle: Near","damage_type":"DamageFalloff","damage_min":"167","damage_max":"200","damage_min_range":"85","damage_max_range":"10","damage_target_type":"2","damage_resist_type":"2"}
,"17224": {"fire_mode_id":17224,"item_id":"7124","type":"primary","description":{"de":"Halbautomatik","en":"Semi-Auto","es":"Semiautomático","fr":"Semi-automatique","it":"Semiautomatico","tr":"Yarı Otomatik"},"player_state_group_id":"2047","cof_recoil":"0.1","reload_time_ms":"3120","reload_chamber_time_ms":"1010","pellets_per_shot":"1","pellet_spread":"0","default_zoom":"1","muzzle_velocity":"550","speed":"550","projectile_description":"TR Assault Rifle: Near","damage_type":"DamageFalloff","damage_min":"100","damage_max":"143","damage_min_range":"60","damage_max_range":"10","damage_target_type":"2","damage_resist_type":"2"}
,"17225": {"fire_mode_id":17225,"item_id":"10001","type":"primary","description":{"de":"Halbautomatik","en":"Semi-Auto","es":"Semiautomático","fr":"Semi-automatique","it":"Semiautomatico","tr":"Yarı Otomatik"},"player_state_group_id":"2101","cof_recoil":"0.12","reload_time_ms":"2665","reload_chamber_time_ms":"535","pellets_per_shot":"1","pellet_spread":"0","default_zoom":"1","muzzle_velocity":"620","speed":"650","projectile_description":"TR Assault Rifle: Far","damage_type":"DamageFalloff","damage_min":"125","damage_max":"167","damage_min_range":"90","damage_max_range":"10","damage_target_type":"2","damage_resist_type":"2"}
,"17225": {"fire_mode_id":17225,"item_id":"7125","type":"primary","description":{"de":"Halbautomatik","en":"Semi-Auto","es":"Semiautomático","fr":"Semi-automatique","it":"Semiautomatico","tr":"Yarı Otomatik"},"player_state_group_id":"2101","cof_recoil":"0.12","reload_time_ms":"2665","reload_chamber_time_ms":"535","pellets_per_shot":"1","pellet_spread":"0","default_zoom":"1","muzzle_velocity":"620","speed":"650","projectile_description":"TR Assault Rifle: Far","damage_type":"DamageFalloff","damage_min":"125","damage_max":"167","damage_min_range":"90","damage_max_range":"10","damage_target_type":"2","damage_resist_type":"2"}
,"17248": {"fire_mode_id":17248,"item_id":"800878","type":"primary","description":{"de":"Halbautomatik","en":"Semi-Auto","es":"Semiautomático","fr":"Semi-automatique","it":"Semiautomatico","tr":"Yarı Otomatik"},"player_state_group_id":"2049","cof_recoil":"0.1","reload_time_ms":"2565","reload_chamber_time_ms":"635","pellets_per_shot":"1","pellet_spread":"0","default_zoom":"1","muzzle_velocity":"570","speed":"565","max_speed":"0","damage_radius":"0","projectile_description":"VS Assault Rifle: Near","damage_type":"DamageFalloff","damage_min":"100","damage_max":"143","damage_min_range":"60","damage_max_range":"10","damage_target_type":"2","damage_resist_type":"2"}
,"17248": {"fire_mode_id":17248,"item_id":"10024","type":"primary","description":{"de":"Halbautomatik","en":"Semi-Auto","es":"Semiautomático","fr":"Semi-automatique","it":"Semiautomatico","tr":"Yarı Otomatik"},"player_state_group_id":"2049","cof_recoil":"0.1","reload_time_ms":"2565","reload_chamber_time_ms":"635","pellets_per_shot":"1","pellet_spread":"0","default_zoom":"1","muzzle_velocity":"570","speed":"565","max_speed":"0","damage_radius":"0","projectile_description":"VS Assault Rifle: Near","damage_type":"DamageFalloff","damage_min":"100","damage_max":"143","damage_min_range":"60","damage_max_range":"10","damage_target_type":"2","damage_resist_type":"2"}
,"17248": {"fire_mode_id":17248,"item_id":"6002852","type":"primary","description":{"de":"Halbautomatik","en":"Semi-Auto","es":"Semiautomático","fr":"Semi-automatique","it":"Semiautomatico","tr":"Yarı Otomatik"},"player_state_group_id":"2049","cof_recoil":"0.1","reload_time_ms":"2565","reload_chamber_time_ms":"635","pellets_per_shot":"1","pellet_spread":"0","default_zoom":"1","muzzle_velocity":"570","speed":"565","max_speed":"0","damage_radius":"0","projectile_description":"VS Assault Rifle: Near","damage_type":"DamageFalloff","damage_min":"100","damage_max":"143","damage_min_range":"60","damage_max_range":"10","damage_target_type":"2","damage_resist_type":"2"}
,"17248": {"fire_mode_id":17248,"item_id":"7148","type":"primary","description":{"de":"Halbautomatik","en":"Semi-Auto","es":"Semiautomático","fr":"Semi-automatique","it":"Semiautomatico","tr":"Yarı Otomatik"},"player_state_group_id":"2049","cof_recoil":"0.1","reload_time_ms":"2565","reload_chamber_time_ms":"635","pellets_per_shot":"1","pellet_spread":"0","default_zoom":"1","muzzle_velocity":"570","speed":"565","max_speed":"0","damage_radius":"0","projectile_description":"VS Assault Rifle: Near","damage_type":"DamageFalloff","damage_min":"100","damage_max":"143","damage_min_range":"60","damage_max_range":"10","damage_target_type":"2","damage_resist_type":"2"}
,"17249": {"fire_mode_id":17249,"item_id":"10025","type":"primary","description":{"de":"Halbautomatik","en":"Semi-Auto","es":"Semiautomático","fr":"Semi-automatique","it":"Semiautomatico","tr":"Yarı Otomatik"},"player_state_group_id":"2103","cof_recoil":"0.1","reload_time_ms":"2000","reload_chamber_time_ms":"340","pellets_per_shot":"1","pellet_spread":"0","default_zoom":"1","muzzle_velocity":"670","speed":"665","projectile_description":"VS Assault Rifle: Far","damage_type":"DamageFalloff","damage_min":"125","damage_max":"143","damage_min_range":"65","damage_max_range":"10","damage_target_type":"2","damage_resist_type":"2"}
,"17249": {"fire_mode_id":17249,"item_id":"7149","type":"primary","description":{"de":"Halbautomatik","en":"Semi-Auto","es":"Semiautomático","fr":"Semi-automatique","it":"Semiautomatico","tr":"Yarı Otomatik"},"player_state_group_id":"2103","cof_recoil":"0.1","reload_time_ms":"2000","reload_chamber_time_ms":"340","pellets_per_shot":"1","pellet_spread":"0","default_zoom":"1","muzzle_velocity":"670","speed":"665","projectile_description":"VS Assault Rifle: Far","damage_type":"DamageFalloff","damage_min":"125","damage_max":"143","damage_min_range":"65","damage_max_range":"10","damage_target_type":"2","damage_resist_type":"2"}
,"17272": {"fire_mode_id":17272,"item_id":"800880","type":"secondary","description":{"de":"Halbautomatik","en":"Semi-Auto","es":"Semiautomático","fr":"Semi-automatique","it":"Semiautomatico","tr":"Yarı Otomatik"},"player_state_group_id":"2046","cof_recoil":"0.05","reload_time_ms":"2455","reload_chamber_time_ms":"845","pellets_per_shot":"1","pellet_spread":"0","default_zoom":"1.35","muzzle_velocity":"600","speed":"600","max_speed":"0","projectile_description":"NC Assault Rifle: Mid","damage_type":"DamageFalloff","damage_min":"100","damage_max":"143","damage_min_range":"60","damage_max_range":"10","damage_target_type":"2","damage_resist_type":"2"}
,"17272": {"fire_mode_id":17272,"item_id":"50020","type":"secondary","description":{"de":"Halbautomatik","en":"Semi-Auto","es":"Semiautomático","fr":"Semi-automatique","it":"Semiautomatico","tr":"Yarı Otomatik"},"player_state_group_id":"2046","cof_recoil":"0.05","reload_time_ms":"2455","reload_chamber_time_ms":"845","pellets_per_shot":"1","pellet_spread":"0","default_zoom":"1.35","muzzle_velocity":"600","speed":"600","max_speed":"0","projectile_description":"NC Assault Rifle: Mid","damage_type":"DamageFalloff","damage_min":"100","damage_max":"143","damage_min_range":"60","damage_max_range":"10","damage_target_type":"2","damage_resist_type":"2"}
,"17272": {"fire_mode_id":17272,"item_id":"73","type":"secondary","description":{"de":"Halbautomatik","en":"Semi-Auto","es":"Semiautomático","fr":"Semi-automatique","it":"Semiautomatico","tr":"Yarı Otomatik"},"player_state_group_id":"2046","cof_recoil":"0.05","reload_time_ms":"2455","reload_chamber_time_ms":"845","pellets_per_shot":"1","pellet_spread":"0","default_zoom":"1.35","muzzle_velocity":"600","speed":"600","max_speed":"0","projectile_description":"NC Assault Rifle: Mid","damage_type":"DamageFalloff","damage_min":"100","damage_max":"143","damage_min_range":"60","damage_max_range":"10","damage_target_type":"2","damage_resist_type":"2"}
,"17272": {"fire_mode_id":17272,"item_id":"6002896","type":"secondary","description":{"de":"Halbautomatik","en":"Semi-Auto","es":"Semiautomático","fr":"Semi-automatique","it":"Semiautomatico","tr":"Yarı Otomatik"},"player_state_group_id":"2046","cof_recoil":"0.05","reload_time_ms":"2455","reload_chamber_time_ms":"845","pellets_per_shot":"1","pellet_spread":"0","default_zoom":"1.35","muzzle_velocity":"600","speed":"600","max_speed":"0","projectile_description":"NC Assault Rifle: Mid","damage_type":"DamageFalloff","damage_min":"100","damage_max":"143","damage_min_range":"60","damage_max_range":"10","damage_target_type":"2","damage_resist_type":"2"}
,"17272": {"fire_mode_id":17272,"item_id":"920","type":"secondary","description":{"de":"Halbautomatik","en":"Semi-Auto","es":"Semiautomático","fr":"Semi-automatique","it":"Semiautomatico","tr":"Yarı Otomatik"},"player_state_group_id":"2046","cof_recoil":"0.05","reload_time_ms":"2455","reload_chamber_time_ms":"845","pellets_per_shot":"1","pellet_spread":"0","default_zoom":"1.35","muzzle_velocity":"600","speed":"600","max_speed":"0","projectile_description":"NC Assault Rifle: Mid","damage_type":"DamageFalloff","damage_min":"100","damage_max":"143","damage_min_range":"60","damage_max_range":"10","damage_target_type":"2","damage_resist_type":"2"}
,"17280": {"fire_mode_id":17280,"item_id":"7108","type":"secondary","description":{"de":"Halbautomatik","en":"Semi-Auto","es":"Semiautomático","fr":"Semi-automatique","it":"Semiautomatico","tr":"Yarı Otomatik"},"player_state_group_id":"2100","cof_recoil":"0.07","reload_time_ms":"1925","reload_chamber_time_ms":"640","pellets_per_shot":"1","pellet_spread":"0","default_zoom":"1.35","muzzle_velocity":"615","speed":"550","max_speed":"0","damage_radius":"0","projectile_description":"NC Assault Rifle: Near","damage_type":"DamageFalloff","damage_min":"167","damage_max":"200","damage_min_range":"85","damage_max_range":"10","damage_target_type":"2","damage_resist_type":"2"}
,"17296": {"fire_mode_id":17296,"item_id":"7124","type":"secondary","description":{"de":"Halbautomatik","en":"Semi-Auto","es":"Semiautomático","fr":"Semi-automatique","it":"Semiautomatico","tr":"Yarı Otomatik"},"player_state_group_id":"2048","cof_recoil":"0.05","reload_time_ms":"3120","reload_chamber_time_ms":"1010","pellets_per_shot":"1","pellet_spread":"0","default_zoom":"1.35","muzzle_velocity":"550","speed":"550","projectile_description":"TR Assault Rifle: Near","damage_type":"DamageFalloff","damage_min":"100","damage_max":"143","damage_min_range":"60","damage_max_range":"10","damage_target_type":"2","damage_resist_type":"2"}
,"17297": {"fire_mode_id":17297,"item_id":"7125","type":"secondary","description":{"de":"Halbautomatik","en":"Semi-Auto","es":"Semiautomático","fr":"Semi-automatique","it":"Semiautomatico","tr":"Yarı Otomatik"},"player_state_group_id":"2102","cof_recoil":"0.06","reload_time_ms":"2665","reload_chamber_time_ms":"535","pellets_per_shot":"1","pellet_spread":"0","default_zoom":"1.35","muzzle_velocity":"620","speed":"650","projectile_description":"TR Assault Rifle: Far","damage_type":"DamageFalloff","damage_min":"125","damage_max":"167","damage_min_range":"90","damage_max_range":"10","damage_target_type":"2","damage_resist_type":"2"}
,"17297": {"fire_mode_id":17297,"item_id":"10001","type":"secondary","description":{"de":"Halbautomatik","en":"Semi-Auto","es":"Semiautomático","fr":"Semi-automatique","it":"Semiautomatico","tr":"Yarı Otomatik"},"player_state_group_id":"2102","cof_recoil":"0.06","reload_time_ms":"2665","reload_chamber_time_ms":"535","pellets_per_shot":"1","pellet_spread":"0","default_zoom":"1.35","muzzle_velocity":"620","speed":"650","projectile_description":"TR Assault Rifle: Far","damage_type":"DamageFalloff","damage_min":"125","damage_max":"167","damage_min_range":"90","damage_max_range":"10","damage_target_type":"2","damage_resist_type":"2"}
,"17320": {"fire_mode_id":17320,"item_id":"6002852","type":"secondary","description":{"de":"Halbautomatik","en":"Semi-Auto","es":"Semiautomático","fr":"Semi-automatique","it":"Semiautomatico","tr":"Yarı Otomatik"},"player_state_group_id":"2050","cof_recoil":"0.05","reload_time_ms":"2565","reload_chamber_time_ms":"635","pellets_per_shot":"1","pellet_spread":"0","default_zoom":"1.35","muzzle_velocity":"570","speed":"565","max_speed":"0","damage_radius":"0","projectile_description":"VS Assault Rifle: Near","damage_type":"DamageFalloff","damage_min":"100","damage_max":"143","damage_min_range":"60","damage_max_range":"10","damage_target_type":"2","damage_resist_type":"2"}
,"17320": {"fire_mode_id":17320,"item_id":"7148","type":"secondary","description":{"de":"Halbautomatik","en":"Semi-Auto","es":"Semiautomático","fr":"Semi-automatique","it":"Semiautomatico","tr":"Yarı Otomatik"},"player_state_group_id":"2050","cof_recoil":"0.05","reload_time_ms":"2565","reload_chamber_time_ms":"635","pellets_per_shot":"1","pellet_spread":"0","default_zoom":"1.35","muzzle_velocity":"570","speed":"565","max_speed":"0","damage_radius":"0","projectile_description":"VS Assault Rifle: Near","damage_type":"DamageFalloff","damage_min":"100","damage_max":"143","damage_min_range":"60","damage_max_range":"10","damage_target_type":"2","damage_resist_type":"2"}
,"17320": {"fire_mode_id":17320,"item_id":"10024","type":"secondary","description":{"de":"Halbautomatik","en":"Semi-Auto","es":"Semiautomático","fr":"Semi-automatique","it":"Semiautomatico","tr":"Yarı Otomatik"},"player_state_group_id":"2050","cof_recoil":"0.05","reload_time_ms":"2565","reload_chamber_time_ms":"635","pellets_per_shot":"1","pellet_spread":"0","default_zoom":"1.35","muzzle_velocity":"570","speed":"565","max_speed":"0","damage_radius":"0","projectile_description":"VS Assault Rifle: Near","damage_type":"DamageFalloff","damage_min":"100","damage_max":"143","damage_min_range":"60","damage_max_range":"10","damage_target_type":"2","damage_resist_type":"2"}
,"17320": {"fire_mode_id":17320,"item_id":"800878","type":"secondary","description":{"de":"Halbautomatik","en":"Semi-Auto","es":"Semiautomático","fr":"Semi-automatique","it":"Semiautomatico","tr":"Yarı Otomatik"},"player_state_group_id":"2050","cof_recoil":"0.05","reload_time_ms":"2565","reload_chamber_time_ms":"635","pellets_per_shot":"1","pellet_spread":"0","default_zoom":"1.35","muzzle_velocity":"570","speed":"565","max_speed":"0","damage_radius":"0","projectile_description":"VS Assault Rifle: Near","damage_type":"DamageFalloff","damage_min":"100","damage_max":"143","damage_min_range":"60","damage_max_range":"10","damage_target_type":"2","damage_resist_type":"2"}
,"17321": {"fire_mode_id":17321,"item_id":"7149","type":"secondary","description":{"de":"Halbautomatik","en":"Semi-Auto","es":"Semiautomático","fr":"Semi-automatique","it":"Semiautomatico","tr":"Yarı Otomatik"},"player_state_group_id":"2104","cof_recoil":"0.05","reload_time_ms":"2000","reload_chamber_time_ms":"340","pellets_per_shot":"1","pellet_spread":"0","default_zoom":"1.35","muzzle_velocity":"670","speed":"665","projectile_description":"VS Assault Rifle: Far","damage_type":"DamageFalloff","damage_min":"125","damage_max":"143","damage_min_range":"65","damage_max_range":"10","damage_target_type":"2","damage_resist_type":"2"}
,"17321": {"fire_mode_id":17321,"item_id":"10025","type":"secondary","description":{"de":"Halbautomatik","en":"Semi-Auto","es":"Semiautomático","fr":"Semi-automatique","it":"Semiautomatico","tr":"Yarı Otomatik"},"player_state_group_id":"2104","cof_recoil":"0.05","reload_time_ms":"2000","reload_chamber_time_ms":"340","pellets_per_shot":"1","pellet_spread":"0","default_zoom":"1.35","muzzle_velocity":"670","speed":"665","projectile_description":"VS Assault Rifle: Far","damage_type":"DamageFalloff","damage_min":"125","damage_max":"143","damage_min_range":"65","damage_max_range":"10","damage_target_type":"2","damage_resist_type":"2"}
,"17341": {"fire_mode_id":17341,"item_id":"7169","type":"primary","description":{"de":"Halbautomatik","en":"Semi-Auto","es":"Semiautomático","fr":"Semi-automatique","it":"Semiautomatico","tr":"Yarı Otomatik"},"player_state_group_id":"2105","cof_recoil":"0.1","reload_time_ms":"2700","reload_chamber_time_ms":"300","pellets_per_shot":"1","pellet_spread":"0","default_zoom":"1","muzzle_velocity":"500","speed":"450","max_speed":"0","damage_radius":"0","projectile_description":"NC Carbine: Near","damage_type":"DamageFalloff","damage_min":"100","damage_max":"143","damage_min_range":"60","damage_max_range":"10","damage_target_type":"2","damage_resist_type":"2"}
,"17342": {"fire_mode_id":17342,"item_id":"10046","type":"primary","description":{"de":"Halbautomatik","en":"Semi-Auto","es":"Semiautomático","fr":"Semi-automatique","it":"Semiautomatico","tr":"Yarı Otomatik"},"player_state_group_id":"2107","cof_recoil":"0.14","reload_time_ms":"2045","reload_chamber_time_ms":"695","pellets_per_shot":"1","pellet_spread":"0","default_zoom":"1","muzzle_velocity":"520","speed":"450","max_speed":"0","damage_radius":"0","projectile_description":"NC Carbine: Near","damage_type":"DamageFalloff","damage_min":"143","damage_max":"200","damage_min_range":"80","damage_max_range":"10","damage_target_type":"2","damage_resist_type":"2"}
,"17342": {"fire_mode_id":17342,"item_id":"7170","type":"primary","description":{"de":"Halbautomatik","en":"Semi-Auto","es":"Semiautomático","fr":"Semi-automatique","it":"Semiautomatico","tr":"Yarı Otomatik"},"player_state_group_id":"2107","cof_recoil":"0.14","reload_time_ms":"2045","reload_chamber_time_ms":"695","pellets_per_shot":"1","pellet_spread":"0","default_zoom":"1","muzzle_velocity":"520","speed":"450","max_speed":"0","damage_radius":"0","projectile_description":"NC Carbine: Near","damage_type":"DamageFalloff","damage_min":"143","damage_max":"200","damage_min_range":"80","damage_max_range":"10","damage_target_type":"2","damage_resist_type":"2"}
,"17362": {"fire_mode_id":17362,"item_id":"10066","type":"primary","description":{"de":"Halbautomatik","en":"Semi-Auto","es":"Semiautomático","fr":"Semi-automatique","it":"Semiautomatico","tr":"Yarı Otomatik"},"player_state_group_id":"2111","cof_recoil":"0.06","reload_time_ms":"2265","reload_chamber_time_ms":"865","pellets_per_shot":"1","pellet_spread":"0","default_zoom":"1","muzzle_velocity":"570","speed":"550","max_speed":"0","damage_radius":"0","projectile_description":"TR Carbine: Far","damage_type":"DamageFalloff","damage_min":"112","damage_max":"143","damage_min_range":"60","damage_max_range":"10","damage_target_type":"2","damage_resist_type":"2"}
,"17362": {"fire_mode_id":17362,"item_id":"7190","type":"primary","description":{"de":"Halbautomatik","en":"Semi-Auto","es":"Semiautomático","fr":"Semi-automatique","it":"Semiautomatico","tr":"Yarı Otomatik"},"player_state_group_id":"2111","cof_recoil":"0.06","reload_time_ms":"2265","reload_chamber_time_ms":"865","pellets_per_shot":"1","pellet_spread":"0","default_zoom":"1","muzzle_velocity":"570","speed":"550","max_speed":"0","damage_radius":"0","projectile_description":"TR Carbine: Far","damage_type":"DamageFalloff","damage_min":"112","damage_max":"143","damage_min_range":"60","damage_max_range":"10","damage_target_type":"2","damage_resist_type":"2"}
,"17383": {"fire_mode_id":17383,"item_id":"7211","type":"primary","description":{"de":"Halbautomatik","en":"Semi-Auto","es":"Semiautomático","fr":"Semi-automatique","it":"Semiautomatico","tr":"Yarı Otomatik"},"player_state_group_id":"2115","cof_recoil":"0.12","reload_time_ms":"1670","reload_chamber_time_ms":"940","pellets_per_shot":"1","pellet_spread":"0","default_zoom":"1","muzzle_velocity":"515","speed":"515","max_speed":"0","damage_radius":"0","projectile_description":"VS Carbine: Mid","damage_type":"DamageFalloff","damage_min":"125","damage_max":"167","damage_min_range":"70","damage_max_range":"10","damage_target_type":"2","damage_resist_type":"2"}
,"17404": {"fire_mode_id":17404,"item_id":"7169","type":"secondary","description":{"de":"Halbautomatik","en":"Semi-Auto","es":"Semiautomático","fr":"Semi-automatique","it":"Semiautomatico","tr":"Yarı Otomatik"},"player_state_group_id":"2106","cof_recoil":"0.05","reload_time_ms":"2700","reload_chamber_time_ms":"300","pellets_per_shot":"1","pellet_spread":"0","default_zoom":"1.35","muzzle_velocity":"500","speed":"450","max_speed":"0","damage_radius":"0","projectile_description":"NC Carbine: Near","damage_type":"DamageFalloff","damage_min":"100","damage_max":"143","damage_min_range":"60","damage_max_range":"10","damage_target_type":"2","damage_resist_type":"2"}
,"17405": {"fire_mode_id":17405,"item_id":"10046","type":"secondary","description":{"de":"Halbautomatik","en":"Semi-Auto","es":"Semiautomático","fr":"Semi-automatique","it":"Semiautomatico","tr":"Yarı Otomatik"},"player_state_group_id":"2108","cof_recoil":"0.07","reload_time_ms":"2045","reload_chamber_time_ms":"695","pellets_per_shot":"1","pellet_spread":"0","default_zoom":"1.35","muzzle_velocity":"520","speed":"450","max_speed":"0","damage_radius":"0","projectile_description":"NC Carbine: Near","damage_type":"DamageFalloff","damage_min":"143","damage_max":"200","damage_min_range":"80","damage_max_range":"10","damage_target_type":"2","damage_resist_type":"2"}
,"17405": {"fire_mode_id":17405,"item_id":"7170","type":"secondary","description":{"de":"Halbautomatik","en":"Semi-Auto","es":"Semiautomático","fr":"Semi-automatique","it":"Semiautomatico","tr":"Yarı Otomatik"},"player_state_group_id":"2108","cof_recoil":"0.07","reload_time_ms":"2045","reload_chamber_time_ms":"695","pellets_per_shot":"1","pellet_spread":"0","default_zoom":"1.35","muzzle_velocity":"520","speed":"450","max_speed":"0","damage_radius":"0","projectile_description":"NC Carbine: Near","damage_type":"DamageFalloff","damage_min":"143","damage_max":"200","damage_min_range":"80","damage_max_range":"10","damage_target_type":"2","damage_resist_type":"2"}
,"17425": {"fire_mode_id":17425,"item_id":"10066","type":"secondary","description":{"de":"Halbautomatik","en":"Semi-Auto","es":"Semiautomático","fr":"Semi-automatique","it":"Semiautomatico","tr":"Yarı Otomatik"},"player_state_group_id":"2112","cof_recoil":"0.05","reload_time_ms":"2265","reload_chamber_time_ms":"865","pellets_per_shot":"1","pellet_spread":"0","default_zoom":"1.35","muzzle_velocity":"570","speed":"550","max_speed":"0","damage_radius":"0","projectile_description":"TR Carbine: Far","damage_type":"DamageFalloff","damage_min":"112","damage_max":"143","damage_min_range":"60","damage_max_range":"10","damage_target_type":"2","damage_resist_type":"2"}
,"17425": {"fire_mode_id":17425,"item_id":"7190","type":"secondary","description":{"de":"Halbautomatik","en":"Semi-Auto","es":"Semiautomático","fr":"Semi-automatique","it":"Semiautomatico","tr":"Yarı Otomatik"},"player_state_group_id":"2112","cof_recoil":"0.05","reload_time_ms":"2265","reload_chamber_time_ms":"865","pellets_per_shot":"1","pellet_spread":"0","default_zoom":"1.35","muzzle_velocity":"570","speed":"550","max_speed":"0","damage_radius":"0","projectile_description":"TR Carbine: Far","damage_type":"DamageFalloff","damage_min":"112","damage_max":"143","damage_min_range":"60","damage_max_range":"10","damage_target_type":"2","damage_resist_type":"2"}
,"17446": {"fire_mode_id":17446,"item_id":"7211","type":"secondary","description":{"de":"Halbautomatik","en":"Semi-Auto","es":"Semiautomático","fr":"Semi-automatique","it":"Semiautomatico","tr":"Yarı Otomatik"},"player_state_group_id":"2116","cof_recoil":"0.06","reload_time_ms":"1670","reload_chamber_time_ms":"940","pellets_per_shot":"1","pellet_spread":"0","default_zoom":"1.35","muzzle_velocity":"515","speed":"515","max_speed":"0","damage_radius":"0","projectile_description":"VS Carbine: Mid","damage_type":"DamageFalloff","damage_min":"125","damage_max":"167","damage_min_range":"70","damage_max_range":"10","damage_target_type":"2","damage_resist_type":"2"}
}
